{"B2": {"box": {"stato_di_conservazione_mediano_della_zona": "normale", "prezzo_acquisto_min": 370.0, "prezzo_acquisto_max": 550.0, "prezzo_acquisto_medio": 460.0, "prezzo_affitto_min": 2.2, "prezzo_affitto_max": 3.3, "prezzo_affitto_medio": 2.8}, "abitazioni_civili": {"stato_di_conservazione_mediano_della_zona": "normale", "prezzo_acquisto_min": 325.0, "prezzo_acquisto_max": 475.0, "prezzo_acquisto_medio": 400.0, "prezzo_affitto_min": 1.9, "prezzo_affitto_max": 2.85, "prezzo_affitto_medio": 2.4}, "abitazioni_di_tipo_economico": {"stato_di_conservazione_mediano_della_zona": "normale", "prezzo_acquisto_min": 470.0, "prezzo_acquisto_max": 700.0, "prezzo_acquisto_medio": 585.0, "prezzo_affitto_min": 3.4, "prezzo_affitto_max": 5.0, "prezzo_affitto_medio": 4.2}}, "E6": {"abitazioni_civili": {"stato_di_conservazione_mediano_della_zona": "normale", "prezzo_acquisto_min": 0.0, "prezzo_acquisto_max": 0.0, "prezzo_affitto_min": 0.0, "prezzo_affitto_max": 0.0}}, "E7": {"abitazioni_civili": {"stato_di_conservazione_mediano_della_zona": "normale", "prezzo_acquisto_min": 0.0, "prezzo_acquisto_max": 0.0, "prezzo_affitto_min": 0.0, "prezzo_affitto_max": 0.0}}, "E8": {"abitazioni_civili": {"stato_di_conservazione_mediano_della_zona": "normale", "prezzo_acquisto_min": 0.0, "prezzo_acquisto_max": 0.0, "prezzo_affitto_min": 0.0, "prezzo_affitto_max": 0.0}}}